ctm_cli/__init__.py
ctm_cli/errors.py
ctm_cli/main.py
src/__init__.py
src/errors.py
src/main.py
ctm_cli-0.2.1.dist-info/METADATA
ctm_cli-0.2.1.dist-info/WHEEL
ctm_cli-0.2.1.dist-info/entry_points.txt
ctm_cli-0.2.1.dist-info/top_level.txt
ctm_cli-0.2.1.dist-info/RECORD
