Metadata-Version: 2.1
Name: ctm-cli
Version: 0.2.1
Summary: A command-line tool for Configuration & Tasks Management
Home-page: https://github.com/gomleksiz/ctm-cli
Author: Huseyin G.
Author-email: huseyim@gmail.com
Classifier: Programming Language :: Python :: 3
Classifier: License :: OSI Approved :: MIT License
Classifier: Operating System :: OS Independent
Requires-Python: >=3.6
Requires-Dist: click (>=8.0.0)
Requires-Dist: pyyaml (>=5.4.1)
Requires-Dist: apscheduler (>=3.7.0)
